fastai_minima/__init__.py
fastai_minima/_nbdev.py
fastai_minima/learner.py
fastai_minima/metrics.py
fastai_minima/optimizer.py
fastai_minima/utils.py
fastai_minima/callback/__init__.py
fastai_minima/callback/core.py
fastai_minima/callback/training.py
fastai_minima/callback/training_utils.py
fastai_minima-0.0.9.dist-info/METADATA
fastai_minima-0.0.9.dist-info/RECORD
fastai_minima-0.0.9.dist-info/WHEEL
fastai_minima-0.0.9.dist-info/entry_points.txt
fastai_minima-0.0.9.dist-info/top_level.txt
