Metadata-Version: 2.1
Name: fastai-minima
Version: 0.0.9
Summary: A minimal version of fastai with only what's needed for the training loop
Home-page: https://github.com/muellerzr/fastai_minima/tree/master/
Author: Zachary Mueller, Jeremy Howard, Sylvain Gugger, and contributors
Author-email: muellerzr@gmail.com
License: Apache Software License 2.0
Keywords: fastai pytorch
Platform: UNKNOWN
Classifier: Development Status :: 6 - Mature
Classifier: Intended Audience :: Developers
Classifier: Natural Language :: English
Classifier: Programming Language :: Python :: 3.6
Classifier: Programming Language :: Python :: 3.7
Classifier: Programming Language :: Python :: 3.8
Classifier: License :: OSI Approved :: Apache Software License
Requires-Python: >=3.6
License-File: LICENSE
Requires-Dist: fastcore (>=1.3.19)
Requires-Dist: fastprogress (>=0.2.4)
Requires-Dist: torch (>=1.7.0)
Requires-Dist: scikit-learn (>=0.24.1)
Requires-Dist: pandas (>=1.1.5)
Requires-Dist: numpy (>=1.19.5)
Requires-Dist: matplotlib (>=3.2.2)
